spkb/__init__.py
spkb/board_mount.py
spkb/key_grid_tester.py
spkb/keycaps.py
spkb/keyswitch/__init__.py
spkb/keyswitch/__main__.py
spkb/keyswitch/base.py
spkb/keyswitch/choc.py
spkb/keyswitch/mx.py
spkb/py.typed
spkb/single_key_pcb.py
spkb/single_tester.py
spkb/switch_plate.py
spkb/types.py
spkb/utils.py
spkb-0.1.1.dist-info/LICENSE
spkb-0.1.1.dist-info/METADATA
spkb-0.1.1.dist-info/WHEEL
spkb-0.1.1.dist-info/RECORD
