Metadata-Version: 2.1
Name: spkb
Version: 0.1.1
Summary: A SolidPython-based library for building custom keyboards with Python and OpenSCAD.
Home-page: https://github.com/whitelynx/spkb
License: BSD-3-Clause
Keywords: keyboard,OpenSCAD
Author: David H. Bronke
Author-email: whitelynx@gmail.com
Requires-Python: >=3.12,<4.0
Classifier: License :: OSI Approved :: BSD License
Classifier: Operating System :: OS Independent
Classifier: Programming Language :: Python :: 3
Classifier: Programming Language :: Python :: 3.12
Classifier: Programming Language :: Python :: 3.13
Requires-Dist: solidpython2 (>=2.1.0,<3.0.0)
Requires-Dist: typing-extensions (>=4.12.2,<5.0.0)
Project-URL: Bug Tracker, https://github.com/whitelynx/spkb/issues
Project-URL: Documentation, https://spkb.readthedocs.io
Project-URL: Repository, https://github.com/whitelynx/spkb
